{
  "movie_id": "ch0a030ed73550489a6cf95bdd8d09a426c8f45a6a",
  "language": "zh",
  "cross_scene_arcs": [
    {
      "arc_id": "v6arc_a91643452fb53fd9",
      "character_name": "张牧之",
      "title": "从复仇到使命：张牧之的斗争目标升维",
      "arc_focus": "goal",
      "linked_timeline_node_ids": [
        "v6tu_0efa8fa51a2c48d2",
        "v6tu_1106d11b3261eadb",
        "v6tu_d1628e26afa410ea",
        "v6tu_d4d4b333db54f305",
        "v6tu_7c4c28c0d4df0026",
        "v6tu_abdc36ea96992918",
        "v6tu_c0b0b6afeb950e67"
      ],
      "arc_summary": "张牧之的行动动机从为六子复仇的个人情感驱动，逐步升华为推翻黄四郎暴政、建立新秩序的公共使命。他不断调整战略目标，从局部对抗到全面揭露罪行，最终确立以合法性和群众基础为核心的斗争逻辑。",
      "start_state": "为兄弟六子报仇的个人复仇",
      "end_state": "以执法者身份公开审判黄四郎，建立新秩序",
      "unresolved_issue": "其理想主义目标是否能在无制度支持下持续实现，仍存疑"
    },
    {
      "arc_id": "v6arc_6ca3b254b8dd17f3",
      "character_name": "张牧之",
      "title": "与黄四郎的宿命对照：从伪装到公开对抗",
      "arc_focus": "conflict",
      "linked_timeline_node_ids": [
        "v6tu_edd1c246ef7e0f21",
        "v6tu_7bdc6cdab2d59530",
        "v6tu_d4d4b333db54f305",
        "v6tu_abdc36ea96992918",
        "v6tu_c0b0b6afeb950e67",
        "v6tu_1204b16daa5826dd"
      ],
      "arc_summary": "张牧之与黄四郎的关系从伪装合作、相互试探，发展为全面揭露与公开对决。两人构成权力、道义与身份的双重镜像，最终在群众注视下完成权力更替的仪式性清算。",
      "start_state": "身份被识破但仍维持合作表象",
      "end_state": "公开宣战并主导对黄四郎的处决仪式",
      "unresolved_issue": "黄四郎背后是否还有更大权力网络未被清除"
    },
    {
      "arc_id": "v6arc_831af3fc1fa2dfe3",
      "character_name": "张牧之",
      "title": "领导权威的建构：从质疑到绝对掌控",
      "arc_focus": "status",
      "linked_timeline_node_ids": [
        "v6tu_5cd322fc5c7acbeb",
        "v6tu_1106d11b3261eadb",
        "v6tu_f734bfec4b6108b2",
        "v6tu_4dab461294d71932",
        "v6tu_fe8fa1304f660828",
        "v6tu_d12f6fe35b7aadb0"
      ],
      "arc_summary": "张牧之通过心理操控、战略远见与仪式化行动，逐步确立不可动摇的领导地位。他从被兄弟质疑的决策者，转变为团队近乎盲从的精神核心，完成权威的内在建构与外在确认。",
      "start_state": "使用暴力与性威胁确立对老汤的支配",
      "end_state": "团队完全信服其战略判断，领导地位达到顶峰",
      "unresolved_issue": "其权威建立在信息不对称与心理操控之上，存在潜在崩塌风险"
    },
    {
      "arc_id": "v6arc_02e3e7ecf23dd2a8",
      "character_name": "张牧之",
      "title": "群众心理的操控与唤醒：从收买到觉醒",
      "arc_focus": "mixed",
      "linked_timeline_node_ids": [
        "v6tu_1106d11b3261eadb",
        "v6tu_c0b0b6afeb950e67",
        "v6tu_f734bfec4b6108b2",
        "v6tu_4dab461294d71932",
        "v6tu_31cb4fc95b8eee0a",
        "v6tu_d12f6fe35b7aadb0"
      ],
      "arc_summary": "张牧之将斗争策略从物质激励（发银）转向心理动员（激发愤怒），通过制造假象、仪式宣示与精准时机控制，逐步唤醒民众的集体意识，实现从个体抗争到群众运动的跃迁。",
      "start_state": "通过分发银两操控民众情绪",
      "end_state": "百姓自发响应枪击，成为反抗同盟",
      "unresolved_issue": "民众觉醒是否真正持久，还是依赖张牧之的持续操控"
    },
    {
      "arc_id": "v6arc_21b7840acef87c72",
      "character_name": "张牧之",
      "title": "身份认同的挣扎与重构",
      "arc_focus": "relationship",
      "linked_timeline_node_ids": [
        "v6tu_edd1c246ef7e0f21",
        "v6tu_7c4c28c0d4df0026",
        "v6tu_71bb1b316f8c462e",
        "v6tu_93b9920e57ca74ee",
        "v6tu_1204b16daa5826dd"
      ],
      "arc_summary": "张牧之在'张麻子''假县长''老天爷''执法者'等多重身份间挣扎，最终通过承接兄弟遗愿与公共使命，完成从身份混淆到主动承担的转变，但其真实自我始终被遮蔽于象征之下。",
      "start_state": "身份暴露，陷入双重身份矛盾",
      "end_state": "公开承担县长使命，但真实身份仍被替身遮蔽",
      "unresolved_issue": "其真实过往与'张麻子'的关联仍未彻底揭晓，身份谜团未完全解开"
    },
    {
      "arc_id": "v6arc_49c323dc9d24bb93",
      "character_name": "老汤",
      "title": "从逃亡者到权力棋子的身份重构",
      "arc_focus": "status",
      "linked_timeline_node_ids": [
        "v6tu_c12dcdd017307470",
        "v6tu_0d56b9bf776f36b6",
        "v6tu_465e9fab18164fca",
        "v6tu_afea5ec470d1b47d"
      ],
      "arc_summary": "老汤从最初抗拒身份绑定的逃亡者，被强行推上'师爷'乃至'县长'象征位置，逐步卷入权力表象体系；他试图维持这一虚假地位以获取安全感，但最终在张牧之的压制下身份被彻底架空，象征性权威全面崩塌。",
      "start_state": "老汤意图逃脱回归自由，抗拒任何官职与权力结构",
      "end_state": "身份被公开质疑，心理防线崩溃，精神陷入绝望，原有身份认同完全瓦解",
      "unresolved_issue": "老汤是否将屈服于胁迫或寻求反击机会，其真实立场仍悬置"
    },
    {
      "arc_id": "v6arc_9502737bd2280f23",
      "character_name": "老汤",
      "title": "忠诚与怀疑之间的信任裂变",
      "arc_focus": "relationship",
      "linked_timeline_node_ids": [
        "v6tu_11988a49b24542ef",
        "v6tu_5f6d47ca9eeab9fb",
        "v6tu_465e9fab18164fca",
        "v6tu_840a65a9bd2225d8",
        "v6tu_4ddd3c17661580fa"
      ],
      "arc_summary": "老汤对张牧之的关系经历了从感恩追随到产生怀疑、再至被揭穿欺骗的剧烈转变；两人关系在亲密与对抗间摇摆，最终因老汤的算计暴露而彻底逆转，信任基础瓦解。",
      "start_state": "老汤信任并追随张牧之，视其为革命领袖与恩人",
      "end_state": "老汤的欺骗被揭穿，情绪由得意转为惊恐，张牧之开始怀疑其全部动机",
      "unresolved_issue": "伏击来源不明，老汤无法判断张牧之是否早已反制，关系走向高度不确定"
    },
    {
      "arc_id": "v6arc_d0851e0580cbd30d",
      "character_name": "老汤",
      "title": "现实生存与道义理想的持续冲突",
      "arc_focus": "conflict",
      "linked_timeline_node_ids": [
        "v6tu_ef57392e1401900a",
        "v6tu_5f6d47ca9eeab9fb",
        "v6tu_ea3c5dd1e604ccf9",
        "v6tu_d4f1a55c6125e9c8",
        "v6tu_6cac0dfa8f8e58f1"
      ],
      "arc_summary": "老汤始终以现实利益和生存安全为核心诉求，与张牧之的理想主义形成根本对立；他在敛财策略、复仇方式、身份处理等关键节点上坚持务实立场，引发团队内部理念冲突，并最终导致与兄弟及张牧之的公开决裂。",
      "start_state": "主张'三七分成'的敛财机制，接受腐败现实以求自保",
      "end_state": "因坚持道德底线与现实诉求与兄弟决裂，成为团队中的孤立者",
      "unresolved_issue": "安全分赃与冒险复仇的根本矛盾未解，老汤的生存哲学是否成立仍受质疑"
    },
    {
      "arc_id": "v6arc_472b2eccba6c6745",
      "character_name": "老汤",
      "title": "从被动求生到认知觉醒的意识转变",
      "arc_focus": "mixed",
      "linked_timeline_node_ids": [
        "v6tu_2eee505b9e8bae42",
        "v6tu_9504f603aee7e8ac",
        "v6tu_70441b3c47a54ff2"
      ],
      "arc_summary": "老汤从最初被动预警、信息提供，逐步发展为主动质疑、情感爆发与认知重构；他经历夫人之死、身份羞辱、骗局揭穿等打击后，完成从依附者到觉醒者的心理跃迁，虽仍受控于局势，但已具备独立判断能力。",
      "start_state": "通过报恩话语试图影响张牧之决策，仍处于旁观者心态",
      "end_state": "在语言崩溃中被迫站队，成为张牧之'至爱'象征，失去自主却获得核心信息",
      "unresolved_issue": "老汤是否真正理解'惊喜'的政治含义及其在新权力结构中的角色仍不明确"
    },
    {
      "arc_id": "v6arc_c9640902bb4cadb6",
      "character_name": "老汤",
      "title": "操控与反噬：权力游戏中的自我颠覆",
      "arc_focus": "goal",
      "linked_timeline_node_ids": [
        "v6tu_13d78227b9683eea",
        "v6tu_4ddd3c17661580fa"
      ],
      "arc_summary": "老汤试图通过身份伪装与政治操盘实现自己上任县长的真实目标，在黄四郎与张牧之之间构建由其主导的权力结构；然而其计谋逐步暴露，最终陷入被反制的危机，野心与生存同时面临终结风险。",
      "start_state": "利用身份混乱构建'假县长—真操盘手'格局，谋求隐蔽掌控鹅城",
      "end_state": "坦承委任状为假及双重预案，计谋败露后遭遇未知伏击，计划濒临崩溃",
      "unresolved_issue": "伏击是黄四郎出手还是张牧之设局尚不明确，老汤的最终命运悬而未决"
    },
    {
      "arc_id": "v6arc_59715bb03a2bcf77",
      "character_name": "黄四郎",
      "title": "角色主线推进",
      "arc_focus": "mixed",
      "linked_timeline_node_ids": [
        "v6tu_da8810e33ee3bee1",
        "v6tu_c5db0b93772161da",
        "v6tu_d61e99c82efed4d1"
      ],
      "arc_summary": "黄四郎从前段的黄四郎通过望远镜确认张牧之到来，目睹其策马入镇及仪式性处决五名麻匪，心理状态由戏谑转为警觉，启动对张牧之的监视与对抗准备，逐步推进到后段的黄四郎在克楼顶上高呼张牧之之名，随后引爆自己，以礼帽飞升的意象完成自我加冕式的死亡，实现其戏剧性终结。，中间节点体现了这条叙事主线的持续演化。",
      "start_state": "从娱乐性训练替身转向严肃应对外来威胁，视张牧之为潜在权力挑战者",
      "end_state": "黄四郎死亡，克楼被炸毁，其家族象征与权力实体彻底瓦解，物理存在与社会影响同时消散。",
      "unresolved_issue": "黄四郎临终呼喊'张牧之——'未获回应，二人宿命对决的深层意义未被张牧之直接承接，留下精神层面的空响。"
    }
  ]
}
