{
  "movie_id": "chad83aa5c1d76c9068cb7f2693704827931d91b36",
  "language": "zh",
  "task_name": "Story Dynamics Structuring",
  "task_version": "workflow_v66_recall_balanced",
  "cross_scene_arcs": [
    {
      "arc_id": "v6arc_b0cc124ee23d97d1",
      "character_name": "大哥",
      "title": "从保护者到家族精神领袖的转变",
      "arc_focus": "status",
      "linked_timeline_node_ids": [
        "v6tu_06d8a45548b8c9c2",
        "v6tu_480f34c44883524c",
        "v6tu_a4af13ab0fdae428",
        "v6tu_4bb634c275b8833e",
        "v6tu_f37aa3c5e0643292",
        "v6tu_fbc009f99768b7bb"
      ],
      "arc_summary": "大哥从最初作为宽美与焕良的直接保护者，逐步在家族危机中展现领导力，最终在谈判中提出关键方案，确立其在家族事务中的决策地位，完成从边缘成员向核心权威的身份过渡。",
      "start_state": "作为兄长试图为妹妹争取独立空间，但担忧父亲权威的否定",
      "end_state": "在正式家族会议中主导局势，其提议获得间接认可，标志其地位上升为实际领导者",
      "unresolved_issue": "大哥的权威尚未完全稳固，仍需面对金泉等外部势力的潜在挑战"
    },
    {
      "arc_id": "v6arc_394d50c08a5f31b1",
      "character_name": "大哥",
      "title": "家庭责任与个人创伤的持续冲突",
      "arc_focus": "conflict",
      "linked_timeline_node_ids": [
        "v6tu_4bb634c275b8833e",
        "v6tu_0a169c71757484d2",
        "v6tu_fbc009f99768b7bb",
        "v6tu_f143405148905b9b",
        "v6tu_759e4fbf90b6f5ee",
        "v6tu_6ae28e3961bd8dc4"
      ],
      "arc_summary": "大哥在承担家族重担的过程中不断遭遇内在心理创伤的反扑，尤其是童年受虐记忆与对父权的复杂情感，导致其在关键时刻虽有担当却难以真正影响决策，最终陷入精神崩溃与现实脱节。",
      "start_state": "在三哥精神失常时情绪崩溃，首次暴露心理防线瓦解",
      "end_state": "在时代剧变面前情感麻木，沉溺于回忆，显示其内心已与现实断裂",
      "unresolved_issue": "童年创伤未愈，枪声幻听持续，大哥能否重建心理连接以应对现实危机仍未知"
    },
    {
      "arc_id": "v6arc_781f8ac719a47ba1",
      "character_name": "大哥",
      "title": "从被动承受命运到主动掌控危机的行动演进",
      "arc_focus": "goal",
      "linked_timeline_node_ids": [
        "v6tu_a8bd528f1e817448",
        "v6tu_539d4c6d0d11cb91",
        "v6tu_f37aa3c5e0643292",
        "v6tu_bcb808b3b1255557",
        "v6tu_3ddc57bacf0ede60",
        "v6tu_14b40b4cdd92b624"
      ],
      "arc_summary": "大哥从最初被动应对家族成员的精神与身体危机，逐步发展为主动介入走私调查、毒品追责与营救弟弟等高风险行动，最终以暴力手段试图夺回控制权，体现其目标从维稳转向主动抗争的演变轨迹。",
      "start_state": "截获走私证据并打破沟通层级，意图直接掌控局势",
      "end_state": "在赌场冲突中刺伤对手，以生命为代价实施最后反击，目标彻底外化为暴力对抗",
      "unresolved_issue": "大哥是否当场死亡未明，其行动所引发的权力真空与家族命运走向悬而未决"
    },
    {
      "arc_id": "v6arc_844fa0c99a5de9dc",
      "character_name": "大哥",
      "title": "与父亲及长辈权威的复杂关系演变",
      "arc_focus": "relationship",
      "linked_timeline_node_ids": [
        "v6tu_06d8a45548b8c9c2",
        "v6tu_0a169c71757484d2",
        "v6tu_1da393f085bfda7c",
        "v6tu_f143405148905b9b"
      ],
      "arc_summary": "大哥始终处于父亲权威的阴影之下，从担忧父亲不认可其对宽美的安排，到试图劝阻阿公却遭压制，再到被警示提防身边人，最终在幻觉中回溯童年创伤，揭示其一生行为深受父权压抑的影响。",
      "start_state": "担忧父亲不认可自己对宽美的安排，反映其判断仍受家庭权威制约",
      "end_state": "在幻听中重现被绑电火柱的记忆，显示父权创伤深植心理底层",
      "unresolved_issue": "大哥是否能摆脱父亲的精神控制，建立自主的亲子或领导模式，未有明确出路"
    },
    {
      "arc_id": "v6arc_4003e1058f1aecfa",
      "character_name": "大哥",
      "title": "政治迫害与兄弟命运的捆绑式危机",
      "arc_focus": "mixed",
      "linked_timeline_node_ids": [
        "v6tu_4e2fc111df87abdf",
        "v6tu_83b9859c9b444298",
        "v6tu_75b9de115ddb6df0",
        "v6tu_bcb808b3b1255557",
        "v6tu_3ddc57bacf0ede60",
        "v6tu_b05b792e2325a3a4"
      ],
      "arc_summary": "大哥在通缉逃亡中接连遭遇弟弟良仔被构陷枪击、官方确认汉奸指控等打击，从被动避难转为主动营救，将个人生存危机与兄弟命运深度绑定，形成一条贯穿后半程的政治与亲情双重压迫弧线。",
      "start_state": "突遭通缉，被迫赤脚逃亡，生活由安定转入流离",
      "end_state": "以白粉为筹码与阿山谈判，正式将营救弟弟内化为不可推卸的使命",
      "unresolved_issue": "国家意识形态压制与兄弟生存之间的根本矛盾无解，营救成功可能性极低"
    },
    {
      "arc_id": "v6arc_bc4281316b9f3c78",
      "character_name": "宽美",
      "title": "从外来者到家族核心：宽美的身份融入与地位转变",
      "arc_focus": "status",
      "linked_timeline_node_ids": [
        "v6tu_eddfd2b33fc4cec2",
        "v6tu_bf7deac45c0e8a2b",
        "v6tu_ef6ab3a94d200e69",
        "v6tu_8eb5e2bd26d8bd61",
        "v6tu_aff604376b0aa416"
      ],
      "arc_summary": "宽美从初抵金瓜石的陌生外来者，逐步通过医院工作、承担家族委托与情感联结，最终以妻子和母亲的身份被林家正式接纳，完成社会身份的根本性跃升。",
      "start_state": "作为外来者初抵金瓜石，语言与文化隔阂明显，身份模糊",
      "end_state": "成为焕清之妻与新生儿之母，被家族公开接纳，确立核心家庭成员地位",
      "unresolved_issue": "丧期成婚带来伦理争议，身份合法性仍面临传统习俗的潜在质疑"
    },
    {
      "arc_id": "v6arc_74516076cc478985",
      "character_name": "宽美",
      "title": "宽美与林焕清：从初识到精神共契的情感深化",
      "arc_focus": "relationship",
      "linked_timeline_node_ids": [
        "v6tu_eddfd2b33fc4cec2",
        "v6tu_5f6ebde601a6623c",
        "v6tu_95618e42b108ea4e",
        "v6tu_eacd73bfb9157645",
        "v6tu_8c96259b6f1a99d5",
        "v6tu_b8019c1373b44d78",
        "v6tu_fd8f9b08c32619ff",
        "v6tu_8eb5e2bd26d8bd61"
      ],
      "arc_summary": "宽美与焕清的关系从初见接应发展为护理中的默契，再经由思想共鸣、情感共情升华为精神伴侣，最终通过婚姻与共同命运绑定，形成贯穿动荡时代的情感主线。",
      "start_state": "初次见面，建立初步人际联系，关系尚属表面",
      "end_state": "通过婚姻完成关系制度化，情感在沉默与诀别中升华为革命伴侣与命运共同体",
      "unresolved_issue": "焕清选择'假死'投身革命，婚姻关系在政治压迫下被迫转入地下，情感联结停留在未竟状态"
    },
    {
      "arc_id": "v6arc_f2916aaac830c4bd",
      "character_name": "宽美",
      "title": "觉醒与承担：宽美从被动执行到主动参与的政治意识成长",
      "arc_focus": "goal",
      "linked_timeline_node_ids": [
        "v6tu_bf7deac45c0e8a2b",
        "v6tu_ef6ab3a94d200e69",
        "v6tu_0d93a8e8176739e1",
        "v6tu_21a5a0b67267db4e",
        "v6tu_51e83563f05ea3d4",
        "v6tu_2dbe20a5f15d640d"
      ],
      "arc_summary": "宽美最初追求个人独立与思想启蒙，逐渐被卷入家庭政治危机，从协助照护转变为逃亡共担者，最终主动选择与焕清共赴险境，完成从旁观者到革命参与者的意志觉醒。",
      "start_state": "目标为脱离家庭束缚，追求独立生活与知识启蒙",
      "end_state": "主动选择与焕清共同逃亡，将个人命运与政治抗争彻底绑定",
      "unresolved_issue": "逃亡方向与生存可能未定，政治参与缺乏组织支持，行动前景充满不确定性"
    },
    {
      "arc_id": "v6arc_4b3d7359c2e6479c",
      "character_name": "宽美",
      "title": "家庭重压下的情感负荷：宽美作为女性支点的心理承受弧",
      "arc_focus": "conflict",
      "linked_timeline_node_ids": [
        "v6tu_348b643a451a7725",
        "v6tu_9a93d5a90ccfdfd4",
        "v6tu_95618e42b108ea4e",
        "v6tu_eacd73bfb9157645",
        "v6tu_21a5a0b67267db4e",
        "v6tu_a99f0a0f35cf47ed",
        "v6tu_51e83563f05ea3d4"
      ],
      "arc_summary": "宽美持续承受家庭政治危机带来的心理压力，从被父亲压制、得知亲人被捕到目睹兄长重伤，情感负荷不断累积，始终在责任与压抑间挣扎，体现女性在动荡中作为情感支点的牺牲性角色。",
      "start_state": "试图维持日常秩序，心理尚处相对稳定状态",
      "end_state": "在亲人接连遭遇变故中情绪崩溃，被迫承担照护与逃亡责任，心理负荷达到临界点",
      "unresolved_issue": "情感压力持续累积却无处疏解，个体心理危机未被关注，长期精神负担可能引发深层创伤"
    },
    {
      "arc_id": "v6arc_2eceb45edcaf46ce",
      "character_name": "宽美",
      "title": "记忆、叙述与传承：宽美作为情感与历史见证者的混合角色发展",
      "arc_focus": "mixed",
      "linked_timeline_node_ids": [
        "v6tu_6c9f5b3faf537cb3",
        "v6tu_ef6ab3a94d200e69",
        "v6tu_95618e42b108ea4e",
        "v6tu_8c96259b6f1a99d5",
        "v6tu_5e80a96ba58a4e2c",
        "v6tu_2bc3c14973610671"
      ],
      "arc_summary": "宽美从静子情感的接收者，成长为家族与革命记忆的承载者，通过阅读、讲述、合影与书信，逐步承担起传递历史伤痛与情感联结的叙述使命，成为连接过去与未来的象征性人物。",
      "start_state": "被动接受静子的情感倾诉，尚未形成回应能力",
      "end_state": "主动通过书信向阿雪传递家庭记忆与情感需求，完成从沉默承受者到叙述主体的转变",
      "unresolved_issue": "关键记忆（如焕清被捕、逃亡经历）仍无法公开讲述，叙述受限于政治压抑，历史真相的完整传承仍遥不可及"
    },
    {
      "arc_id": "v6arc_a0de9e92b1d31060",
      "character_name": "林焕清",
      "title": "从羞涩接应者到情感寄托对象",
      "arc_focus": "relationship",
      "linked_timeline_node_ids": [
        "v6tu_43c7db6068a36453",
        "v6tu_39028006ef8ac864"
      ],
      "arc_summary": "林焕清与宽美从初次见面建立初步信任，发展为在宽美内心中成为带有浪漫色彩的情感寄托，其形象由行动者升华为情感象征。",
      "start_state": "林焕清与宽美陌生，通过纸条交流建立初步信任",
      "end_state": "林焕清虽未出场，但在宽美心中已具备情感重量，成为其共情与隐秘好感的对象",
      "unresolved_issue": "林焕清的真实情感与自我认知仍被遮蔽，其聋哑身份是否阻碍情感回应尚无答案"
    },
    {
      "arc_id": "v6arc_2aa451873e25d6e5",
      "character_name": "林焕清",
      "title": "道德觉醒与保护者身份的确立",
      "arc_focus": "goal",
      "linked_timeline_node_ids": [
        "v6tu_4c11e3e680cda6eb",
        "v6tu_ff191efb9efe2db3"
      ],
      "arc_summary": "林焕清在危机中从被动逃难者转变为积极保护他人、维护集体安全的道德主体，完成角色的深层转变。",
      "start_state": "林焕清在暴民盘查中仍为被动个体，面临生存威胁",
      "end_state": "林焕清主动承担风险，保护陌生人并持续为集体安全贡献力量，成为群体中的关键支柱",
      "unresolved_issue": "其行为带来的心理创伤与精神压力未被疗愈，个体代价未被充分处理"
    },
    {
      "arc_id": "v6arc_c575f2a21c80ae2b",
      "character_name": "林焕清",
      "title": "普通人面对极端暴力的精神历程",
      "arc_focus": "conflict",
      "linked_timeline_node_ids": [
        "v6tu_4c11e3e680cda6eb",
        "v6tu_034cfb81e47ca6b2"
      ],
      "arc_summary": "林焕清在极端情境下经历从伪装求生到直面死亡的心理演变，展现一个普通人如何在压迫中走向精神升华。",
      "start_state": "林焕清在暴民面前伪装身份，内心充满恐惧与颤抖",
      "end_state": "林焕清在监狱中抹去泪水，肃穆接受死亡，完成从恐惧到尊严的转变",
      "unresolved_issue": "其死亡未留下言语遗嘱，精神遗产仅通过行为暗示，意义未被明确传承"
    },
    {
      "arc_id": "v6arc_4ce2a5f165cbd6a9",
      "character_name": "林焕清",
      "title": "无声者的精神成长弧",
      "arc_focus": "mixed",
      "linked_timeline_node_ids": [
        "v6tu_43c7db6068a36453",
        "v6tu_39028006ef8ac864",
        "v6tu_4c11e3e680cda6eb",
        "v6tu_ff191efb9efe2db3",
        "v6tu_034cfb81e47ca6b2"
      ],
      "arc_summary": "作为聋哑人，林焕清以行动而非语言推动关系、道德与存在层面的成长，从羞涩个体成长为被铭记的精神象征。",
      "start_state": "林焕清因聋哑而沉默羞涩，依赖非语言交流建立关系",
      "end_state": "林焕清以沉默姿态完成道德抉择与尊严赴死，其存在本身成为无声的精神宣言",
      "unresolved_issue": "其内在世界始终未被完全揭示，观众无法得知他对爱、牺牲与死亡的全部理解"
    }
  ],
  "build_summary": {
    "selected_focal_character_count": 3,
    "arc_count": 14,
    "elapsed_sec": 1553.58
  }
}